historical_robots/__init__.py
historical_robots/parser.py
historical_robots/scraper.py
historical_robots_txt_parser-0.1.2.dist-info/LICENSE
historical_robots_txt_parser-0.1.2.dist-info/WHEEL
historical_robots_txt_parser-0.1.2.dist-info/METADATA
historical_robots_txt_parser-0.1.2.dist-info/RECORD
