Metadata-Version: 2.1
Name: historical-robots-txt-parser
Version: 0.1.2
Summary: Parses historical robots.txt files from Wayback Machine
Home-page: https://github.com/alexlitel/historical-robots-txt-parser
License: MIT
Keywords: robots.txt,wayback machine,historical data,historical
Author: Alex Litel
Requires-Python: >=3.7,<4.0
Classifier: License :: OSI Approved :: MIT License
Classifier: Programming Language :: Python :: 3
Classifier: Programming Language :: Python :: 3.7
Classifier: Programming Language :: Python :: 3.8
Requires-Dist: requests (>=2.23.0,<3.0.0)
Project-URL: Repository, https://github.com/alexlitel/historical-robots-txt-parser
